longport_stock_server/__init__.py
longport_stock_server/__main__.py
longport_stock_server/main.py
longport_stock_server-0.1.2.dist-info/METADATA
longport_stock_server-0.1.2.dist-info/WHEEL
longport_stock_server-0.1.2.dist-info/entry_points.txt
longport_stock_server-0.1.2.dist-info/RECORD
