Metadata-Version: 2.4
Name: longport-stock-server
Version: 0.1.2
Summary: MCP server for longport stock api
Author-email: Ou Zhencong <ozhencong@gmail.com>
Requires-Python: >=3.10
Requires-Dist: httpx>=0.28.1
Requires-Dist: longport>=2.1.8
Requires-Dist: matplotlib>=3.10.1
Requires-Dist: mcp[cli]>=1.2.1
Requires-Dist: numpy>=2.2.4
Requires-Dist: pandas>=2.2.3
Requires-Dist: scipy>=1.15.2
